pg3d/__init__.py
pg3d/app.py
pg3d/camera.py
pg3d/cube.py
pg3d/matrices.py
pg3d/model.py
pg3d/point.py
pg3d/pyramid.py
pg3d/shape.py
pg3d/tetrahedron.py
pg3d/triangle.py
pg3d/MatrixMath/__init__.py
pg3d/MatrixMath/matrix.py
pg3d-0.1.92.dist-info/LICENSE
pg3d-0.1.92.dist-info/METADATA
pg3d-0.1.92.dist-info/WHEEL
pg3d-0.1.92.dist-info/top_level.txt
pg3d-0.1.92.dist-info/RECORD
