Metadata-Version: 2.1
Name: pg3d
Version: 0.1.92
Home-page: https://github.com/poonchoi/3D-GRAPHICS-ENGINE
Author: Daniele Golzio
Author-email: danielegolzio@gmail.com
Classifier: Programming Language :: Python :: 3
Classifier: License :: OSI Approved :: MIT License
Classifier: Operating System :: OS Independent
Requires-Python: >=3.7
License-File: LICENSE
